{
    "workbench.colorTheme": "Monokai",
    // "window.menuBarVisibility": "toggle",
    "workbench.statusBar.visible": true,
    "exclude": [
        "node_modules",
        "dist"
    ],
    "vim.easymotion": true,
    "vim.sneak": true,
    "vim.incsearch": true,
    "vim.useCtrlKeys": true,
    "vim.hlsearch": true,
    "vim.insertModeKeyBindings": [{
        "before": ["j", "j"],
        "after": ["<Esc>"]
    }],
    "vim.otherModesKeyBindingsNonRecursive": [{
            "before": ["<leader>", "d"],
            "after": ["d", "d"]
        },
        {
            "before": ["<C-n>"],
            "after": [],
            "commands": [{
                "command": ":nohl"
            }]
        }
    ],
    "vim.leader": "<space>",
    "vim.handleKeys": {
        "<C-a>": false,
        "<C-f>": false,
        "<C-c>": false,
        "<C-x>": false,
        "<C-p>": false,
        "<C-v>": false
    },
    "vim.useSystemClipboard": false,
    "vim.overrideCopy": false,
    "editor.fontSize": 13,
    "editor.tabSize": 2,
    "files.associations": {
         // 比如小程序中的 .wxss 这种文件，会把它作为css文件来处理，提供对应的css的语法提示，css的格式化等
        "*.wxss": "css",
        "*.wxml": "html",
        "*.svg": "html",
        "*.xml": "html",
        "*.wxs": "javascript",
        // json注释
        "*.cjson": "jsonc",
        "*.json": "jsonc"
    },
    "emmet.includeLanguages": {
        "wxml": "html"
    },
    //"minapp-vscode.disableAutoConfig": true,
    //"git.openRepositoryInParentFolders": "always",
    //"editor.codeActionsOnSave": {


    //},
    "search.exclude": {
        "**/dist": true,
        "**/uni_modules": true,
        "**/unpackage": true,
         "**/node_modules": true,
        "**/pnpm-lock.yaml": true,
        "**/package-lock.json": true,
        "**/.DS_Store": true,
        "**/.git": true,
        "**/.gitignore": true,
        "**/.idea": true,
        "**/.svn": true,
        "**/.vscode": true,
        "**/build": true,
        "**/dist": true,
        "**/tmp": true,
        "**/yarn.lock": true
    },
    //"security.workspace.trust.untrustedFiles": "open",
    "files.exclude": {
        "**/dist": true,
        "**/mobile/erp": true,
        "**/mobile/erp-src": true,
        "**/mobile/static": true,
        "**/node_modules": true
    },
    "editor.codeActionsOnSave": {
    
    },
    //"editor.wordWrapColumn": 200,
    //"[vue]": {
    //    "editor.defaultFormatter": "octref.vetur"
    //}, // 函数注释

    // ----------------  设置属性、js不自动换行  ----------------
    //"vetur.format.defaultFormatterOptions": {
    //    "js-beautify-html": {
    //        "wrap_attributes": "aligned-multiple" //当超出折行长度时，将属性进行垂直对齐
    //    },
    //    "prettyhtml": {
    //        "printWidth": 100, //每行100字符
    //        "singleQuote": false, //单引号强制转双引号
    //        "wrapAttributes": false,
    //        "sortAttributes": false
     //   }
    //},
    // 这个按用户自身习惯选择
    // "vetur.format.defaultFormatter.html": "js-beautify-html",
    // 让vue中的js按编辑器自带的ts格式进行格式化
    // "vetur.format.defaultFormatter.js": "vscode-typescript",
    // ----------------  设置属性、js不自动换行  ----------------




}
